BitMEXAPIKeyAuthenticator.py
__init__.py
bitmex.py
bitmex-0.2.2.dist-info/DESCRIPTION.rst
bitmex-0.2.2.dist-info/METADATA
bitmex-0.2.2.dist-info/RECORD
bitmex-0.2.2.dist-info/WHEEL
bitmex-0.2.2.dist-info/metadata.json
bitmex-0.2.2.dist-info/top_level.txt
