Metadata-Version: 1.0
Name: bitmex
Version: 0.2.2
Summary: BitMEX API client.
Home-page: https://github.com/bitmex/api-Connectors
Author: Samuel Reed
Author-email: sam@bitmex.com
License: UNKNOWN
Platform: UNKNOWN
